CHANGELOG
MANIFEST.in
README.rst
VERSION
setup.py
django_bower_app.egg-info/PKG-INFO
django_bower_app.egg-info/SOURCES.txt
django_bower_app.egg-info/dependency_links.txt
django_bower_app.egg-info/not-zip-safe
django_bower_app.egg-info/requires.txt
django_bower_app.egg-info/top_level.txt
djangobwr/__init__.py
djangobwr/finders.py
djangobwr/models.py
djangobwr/storage.py
djangobwr/management/__init__.py
djangobwr/management/commands/__init__.py
djangobwr/management/commands/bower_install.py