Metadata-Version: 1.1
Name: django-bower-app
Version: 0.5
Summary: Library to manage bower.json dependancies with ease
Home-page: https://github.com/boblefrag/django-bower-app
Author: Yohann Gabory
Author-email: yohann@gabory.fr
License: UNKNOWN
Platform: UNKNOWN
Classifier: Development Status :: 3 - Alpha
Classifier: License :: OSI Approved :: BSD License
Classifier: Programming Language :: Python :: 2.7
Classifier: Framework :: Django
